CyberGear/__init__.py
CyberGear/shell/__init__.py
CyberGear/shell/usage.py
CyberGear/src/temp.txt
HAMi/__init__.py
HAMi/shell/__init__.py
HAMi/shell/usage.py
HAMi/src/temp.txt
PyCyberGear/__init__.py
PyCyberGear/shell/__init__.py
PyCyberGear/shell/usage.py
PyCyberGear/src/temp.txt
hamlib/__init__.py
hamlib/shell/__init__.py
hamlib/shell/usage.py
hamlib/src/temp.txt
pyhami/__init__.py
pyhami/shell/__init__.py
pyhami/shell/usage.py
pyhami/src/temp.txt
hamlib-0.0.1.dist-info/LICENSE
hamlib-0.0.1.dist-info/METADATA
hamlib-0.0.1.dist-info/WHEEL
hamlib-0.0.1.dist-info/entry_points.txt
hamlib-0.0.1.dist-info/top_level.txt
hamlib-0.0.1.dist-info/zip-safe
hamlib-0.0.1.dist-info/RECORD
